MANIFEST.in
README.rst
setup.py
identeco/__init__.py
identeco/forms.py
identeco/models.py
identeco/store.py
identeco/urls.py
identeco/utils.py
identeco/views.py
identeco.egg-info/PKG-INFO
identeco.egg-info/SOURCES.txt
identeco.egg-info/dependency_links.txt
identeco.egg-info/not-zip-safe
identeco.egg-info/requires.txt
identeco.egg-info/top_level.txt
identeco/templates/identeco/discovery.html
identeco/templates/identeco/identity.html
identeco/templates/identeco/xrds.xml
identeco/templates/identeco/trust/decide.html
identeco/templatetags/__init__.py
identeco/templatetags/identeco.py