Metadata-Version: 1.1
Name: identeco
Version: 0.3.1
Summary: An OpenID Provider for Django
Home-page: https://github.com/eldarion/identeco
Author: Donald Stufft
Author-email: dstufft@eldarion.com
License: BSD
Platform: UNKNOWN
Classifier: Environment :: Web Environment
Classifier: Intended Audience :: Developers
Classifier: License :: OSI Approved :: BSD License
Classifier: Operating System :: OS Independent
Classifier: Programming Language :: Python
Classifier: Framework :: Django
